<?xml version="1.0" encoding="UTF-8"?>
<con:soapui-project id="4434fb65-e0a2-4d50-b765-765537035419" created="3.50.0" activeEnvironment="Default environment" encryptionMode="Not encrypted" name="REST Project 2" projectVersion="" updated="3.50.0 2023-12-13T08:40:33Z" xmlns:con="http://eviware.com/soapui/config">
  <con:settings/>
  <con:interface xsi:type="con:RestService" id="3e4a13d7-38f6-48f9-8232-38ac23f9d8d3" wadlVersion="http://wadl.dev.java.net/2009/02" name="https://petstore.swagger.io" type="rest" xmlns:xsi="http://www.w3.org/2001/XMLSchema-instance">
    <con:settings id="9af28f5a-cc17-49c6-b971-05fbbfa14a8f"/>
    <con:definitionCache type="TEXT" rootPart=""/>
    <con:endpoints>
      <con:endpoint>https://petstore.swagger.io</con:endpoint>
    </con:endpoints>
    <con:resource name="" path="/" id="3aed3669-42ce-4aa8-8c5c-c60ad8c21ba5">
      <con:settings/>
      <con:parameters/>
      <con:method name="" id="7684d72a-e183-415b-9cd4-acd00ef21dbc" method="POST">
        <con:settings/>
        <con:parameters/>
        <con:request name="Request 1" id="d40a47c0-d51e-4bf1-aeac-3e465ac199bb" mediaType="application/json">
          <con:settings/>
          <con:endpoint>https://petstore.swagger.io</con:endpoint>
          <con:credentials>
            <con:selectedAuthProfile>No Authorization</con:selectedAuthProfile>
            <con:authType>No Authorization</con:authType>
          </con:credentials>
          <con:parameters/>
        </con:request>
      </con:method>
    </con:resource>
    <con:resource name="Pet" path="/v2/pet" id="31590004-8d74-4e54-a7fe-39f29b5de545">
      <con:settings/>
      <con:parameters/>
      <con:method name="Pet" id="6a7d722f-5473-420c-91c4-9f7f91fc7067" method="GET">
        <con:settings/>
        <con:parameters/>
        <con:request name="Request 1" id="753caf2d-1f50-4f59-b7ca-6c428821411a" mediaType="application/json">
          <con:settings/>
          <con:endpoint>https://petstore.swagger.io</con:endpoint>
          <con:request/>
          <con:credentials>
            <con:selectedAuthProfile>No Authorization</con:selectedAuthProfile>
            <con:authType>No Authorization</con:authType>
          </con:credentials>
          <con:jmsConfig JMSDeliveryMode="PERSISTENT"/>
          <con:parameters/>
        </con:request>
      </con:method>
    </con:resource>
  </con:interface>
  <con:testSuite id="a611c79b-3fef-475c-84f1-e93fa9ad30d9" name="https://petstore.swagger.io Test Suite">
    <con:settings id="df50cecf-7c27-4eb7-adcf-16484bb74b3f"/>
    <con:runType>SEQUENTIAL</con:runType>
    <con:testCase id="18b37ffc-39d9-44fa-bc3d-a144958afe5c" discardOkResults="false" failOnError="false" failTestCaseOnErrors="true" keepSession="false" name="Test Case" searchProperties="true" timeout="0">
      <con:settings/>
      <con:testStep type="datasink" name="Data Sink" id="3701d1fa-2fc4-4a5b-9ae3-99a36870266a">
        <con:settings/>
        <con:config xsi:type="con:DataSinkStep" xmlns:xsi="http://www.w3.org/2001/XMLSchema-instance">
          <con:properties/>
        </con:config>
      </con:testStep>
      <con:testStep type="datasource" name="Data Source" id="dc159955-853e-4f1a-a97c-34be00e4f719">
        <con:settings>
          <con:setting id="com.eviware.soapui.impl.wsdl.teststeps.datasource.DataSourceContainer@prepared-properties">&lt;xml-fragment/></con:setting>
        </con:settings>
        <con:config xsi:type="con:DataSourceStep" xmlns:xsi="http://www.w3.org/2001/XMLSchema-instance">
          <con:dataSource type="Excel">
            <con:configuration>
              <file/>
              <worksheet/>
              <cell>A1</cell>
              <ignoreEmpty>false</ignoreEmpty>
              <evaluateFormulas>false</evaluateFormulas>
            </con:configuration>
          </con:dataSource>
          <con:shared>true</con:shared>
          <con:restartShared>true</con:restartShared>
          <con:property>Form editor is not applicable for this request</con:property>
          <con:property>petID</con:property>
          <con:property>Petname</con:property>
          <con:property>petstatus</con:property>
          <con:completeLastOperation>true</con:completeLastOperation>
          <con:restartOnRun>true</con:restartOnRun>
          <con:stopDatasourceExhausted>false</con:stopDatasourceExhausted>
        </con:config>
      </con:testStep>
      <con:testStep type="restrequest" name="Request 1" id="d4f281e5-a429-4e71-a33c-bb1cfd6cbf04">
        <con:settings/>
        <con:config service="https://petstore.swagger.io" resourcePath="/" methodName="" xsi:type="con:RestRequestStep" xmlns:xsi="http://www.w3.org/2001/XMLSchema-instance">
          <con:restRequest name="Request 1" id="d40a47c0-d51e-4bf1-aeac-3e465ac199bb" mediaType="application/json" postQueryString="false">
            <con:settings/>
            <con:endpoint>https://petstore.swagger.io</con:endpoint>
            <con:request/>
            <con:assertion type="Valid HTTP Status Codes" id="b9711f09-e57b-4bd9-9214-275b027e5703" name="Valid HTTP Status Codes">
              <con:settings/>
              <con:configuration>
                <codes>200</codes>
              </con:configuration>
            </con:assertion>
            <con:credentials>
              <con:selectedAuthProfile>No Authorization</con:selectedAuthProfile>
              <con:authType>No Authorization</con:authType>
            </con:credentials>
            <con:jmsConfig JMSDeliveryMode="PERSISTENT"/>
            <con:parameters/>
          </con:restRequest>
        </con:config>
      </con:testStep>
      <con:testStep type="restrequest" name="Request 2" id="d6f06a4a-be70-4611-9ebc-7ceb554a11cf">
        <con:settings/>
        <con:config service="https://petstore.swagger.io" resourcePath="/v2/pet" methodName="Pet" xsi:type="con:RestRequestStep" xmlns:xsi="http://www.w3.org/2001/XMLSchema-instance">
          <con:restRequest name="Request 2" id="753caf2d-1f50-4f59-b7ca-6c428821411a" mediaType="application/json">
            <con:settings/>
            <con:endpoint>https://petstore.swagger.io</con:endpoint>
            <con:request/>
            <con:assertion type="Valid HTTP Status Codes" id="509f80c7-6424-405c-be37-48613a79c75e" name="Valid HTTP Status Codes">
              <con:settings/>
              <con:configuration>
                <codes>200</codes>
              </con:configuration>
            </con:assertion>
            <con:credentials>
              <con:selectedAuthProfile>No Authorization</con:selectedAuthProfile>
              <con:authType>No Authorization</con:authType>
            </con:credentials>
            <con:jmsConfig JMSDeliveryMode="PERSISTENT"/>
            <con:parameters/>
          </con:restRequest>
        </con:config>
      </con:testStep>
      <con:testStep type="datasourceloop" name="Data Source Loop" id="92fe14ff-7a02-4985-8b1f-d740af8a0f61">
        <con:settings/>
        <con:config>
          <dataSourceStep>Data Source</dataSourceStep>
          <targetStep>Request 1</targetStep>
          <discardResults>true</discardResults>
        </con:config>
      </con:testStep>
      <con:testStep type="transfer" name="Property Transfer" id="d272aa45-98b0-4161-9e5f-ec0fd87c363d">
        <con:settings/>
        <con:config xsi:type="con:PropertyTransfersStep" xmlns:xsi="http://www.w3.org/2001/XMLSchema-instance"/>
      </con:testStep>
      <con:properties/>
      <con:reportParameters/>
    </con:testCase>
    <con:properties/>
    <con:reportParameters/>
  </con:testSuite>
  <con:properties/>
  <con:wssContainer/>
  <con:databaseConnectionContainer/>
  <con:jmsConnectionContainer/>
  <con:oAuth2ProfileContainer/>
  <con:oAuth1ProfileContainer/>
  <con:reporting>
    <con:xmlTemplates/>
    <con:parameters/>
  </con:reporting>
  <con:eventHandlers type="RequestFilter.filterRequest" name="RequestFilter.filterRequest">
    <con:script>// Sample event script to add custom HTTP header to all outgoing REST, SOAP and HTTP(S) calls
// This code is often used for adding custom authentication to ReadyAPI functional tests

// If hardcoding the token, uncomment and change line 5
// token = '4567'

// If your token is parameterized in Project level custom property, uncomment line 8
// token = request.parent.testCase.testSuite.project.getProperty('auth_token').getValue()

// To modify all outgoing calls, remove comments from lines 11 to 16
// headers = request.requestHeaders
// if (headers.containsKey('auth_token2') == false) {
//   headers.put('auth_token2', token)
//   request.requestHeaders = headers
// }</con:script>
  </con:eventHandlers>
  <con:eventHandlers type="TestRunListener.afterStep" name="TestRunListener.afterStep">
    <con:script>// Save all test step results into files
// Change the directory path in line 5 to a location where you want to store details
// then uncomment lines 5 to 10

// filePath = 'C:\\tempOutputDirectory\\'
// fos = new java.io.FileOutputStream(filePath + testStepResult.testStep.label + '.txt', true)
// pw = new java.io.PrintWriter(fos)
// testStepResult.writeTo(pw)
// pw.close()
// fos.close()</con:script>
  </con:eventHandlers>
  <con:authRepository/>
  <con:tags/>
</con:soapui-project>
